reiberdiagram/__init__.py
reiberdiagram/constants.py
reiberdiagram/main.py
reiberdiagram-1.0.8.dist-info/LICENSE
reiberdiagram-1.0.8.dist-info/METADATA
reiberdiagram-1.0.8.dist-info/WHEEL
reiberdiagram-1.0.8.dist-info/RECORD
