Metadata-Version: 2.3
Name: reiberdiagram
Version: 1.0.8
Summary: Package for creating diagrams aiding CSF diagnostics
Home-page: https://github.com/sk359/reiberdiagram
Author: Stephan Knopp
Author-email: stephan_knopp@yahoo.de
Requires-Python: >=3.10,<4.0
Classifier: Programming Language :: Python :: 3
Classifier: Programming Language :: Python :: 3.10
Classifier: Programming Language :: Python :: 3.11
Classifier: Programming Language :: Python :: 3.12
Classifier: Programming Language :: Python :: 3.13
Requires-Dist: coverage (>=7.6.10,<8.0.0)
Requires-Dist: matplotlib (>=3.10.0,<4.0.0)
Project-URL: Repository, https://github.com/sk359/reiberdiagram
